nidsdata/__init__.py
nidsdata/kddcup99/README.md
nidsdata/kddcup99/__init__.py
nidsdata/nslkdd/__init__.py
nidsdata/unswnb15/__init__.py
nidsdata-0.0.3.dist-info/LICENSE
nidsdata-0.0.3.dist-info/METADATA
nidsdata-0.0.3.dist-info/WHEEL
nidsdata-0.0.3.dist-info/top_level.txt
nidsdata-0.0.3.dist-info/RECORD
