Metadata-Version: 2.1
Name: nidsdata
Version: 0.0.3
Summary: NIDS Dataset
Home-page: https://github.com/zhmhbest/python-nidsdata
Author: zhmh
Author-email: zhmhbest@gmail.com
License: MIT
Keywords: nids data
Platform: UNKNOWN
Classifier: Programming Language :: Python :: 3
Classifier: License :: OSI Approved :: MIT License
Classifier: Operating System :: OS Independent
Requires-Python: >=3
Requires-Dist: pandas (>=0.24.2)
Requires-Dist: numpy (>=1.14.0)
Requires-Dist: python-zhmh (>=0.0.8)
